molll/__init__.py
molll/_version.py
molll/molll.py
molll/propll.py
molll/precomputed/__init__.py
molll/precomputed/libinventLL.py
molll/precomputed/data/AtomLL_libinvent_radius_1.json
molll/precomputed/data/AtomLL_libinvent_radius_2.json
molll/precomputed/data/AtomLL_libinvent_radius_3.json
molll/precomputed/data/MolLL_libinvent_radius_1.json
molll/precomputed/data/MolLL_libinvent_radius_2.json
molll/precomputed/data/MolLL_libinvent_radius_3.json
molecule_ll-0.1.2.dist-info/LICENSE
molecule_ll-0.1.2.dist-info/METADATA
molecule_ll-0.1.2.dist-info/WHEEL
molecule_ll-0.1.2.dist-info/top_level.txt
molecule_ll-0.1.2.dist-info/RECORD
