Metadata-Version: 2.1
Name: molecule_ll
Version: 0.1.2
Summary: Log likelihood estimation of molecules.
Author: Esben Jannik Bjerrum
License: GNU LESSER GENERAL PUBLIC LICENSE
Project-URL: Homepage, https://github.com/EBjerrum/molll
Project-URL: Repository, https://github.com/EBjerrum/molll.git
Keywords: probability,molecule,chemistry
Requires-Python: >=3.7
License-File: LICENSE
Requires-Dist: rdkit
Requires-Dist: scikit-mol
